API_callers/__init__.py
API_callers/base.py
API_callers/callers.py
API_callers/user.py
API_callers-0.2.1.dist-info/AUTHORS.rst
API_callers-0.2.1.dist-info/LICENSE
API_callers-0.2.1.dist-info/METADATA
API_callers-0.2.1.dist-info/WHEEL
API_callers-0.2.1.dist-info/top_level.txt
API_callers-0.2.1.dist-info/RECORD
