Metadata-Version: 2.1
Name: API-callers
Version: 0.2.1
Summary: A set of tools to work with JWT APIs
Home-page: https://github.com/williamcaesar/API_callers
Author: William Caesar
Author-email: williamcaesar@pm.me
License: GNU General Public License v3
Keywords: API_callers
Platform: UNKNOWN
Classifier: Development Status :: 2 - Pre-Alpha
Classifier: Intended Audience :: Developers
Classifier: License :: OSI Approved :: GNU General Public License v3 (GPLv3)
Classifier: Natural Language :: English
Classifier: Programming Language :: Python :: 3
Classifier: Programming Language :: Python :: 3.4
Classifier: Programming Language :: Python :: 3.5
Classifier: Programming Language :: Python :: 3.6
Classifier: Programming Language :: Python :: 3.7
Requires-Dist: requests
